c/__init__.py
c/cutil.py
ego_c-1.0.1.dist-info/METADATA
ego_c-1.0.1.dist-info/WHEEL
ego_c-1.0.1.dist-info/top_level.txt
ego_c-1.0.1.dist-info/RECORD
