Metadata-Version: 2.1
Name: ego-c
Version: 1.0.1
Summary: python package
Home-page: https://code.byted.org/content/ego_c
Author: weijingjing.jj
Author-email: weijingjing.jj@bytedance.com
Project-URL: Bug Tracker, https://code.byted.org/content/ego_c/issues
Classifier: Programming Language :: Python :: 3
Classifier: License :: OSI Approved :: MIT License
Classifier: Operating System :: OS Independent
Requires-Python: >=3.6
Requires-Dist: requests
